Repometrics_CLI/__init__.py
Repometrics_CLI/file_extension.py
Repometrics_CLI/repom.py
Repometrics_CLI-0.0.4.dist-info/LICENSE
Repometrics_CLI-0.0.4.dist-info/METADATA
Repometrics_CLI-0.0.4.dist-info/WHEEL
Repometrics_CLI-0.0.4.dist-info/entry_points.txt
Repometrics_CLI-0.0.4.dist-info/top_level.txt
Repometrics_CLI-0.0.4.dist-info/RECORD
