Metadata-Version: 2.1
Name: Repometrics-CLI
Version: 0.0.4
Summary: CLI to display repository files programing languages.
Home-page: https://github.com/Edward1101/Repometrics_CLI
Author: Edward Li Shuyao
Author-email: lishuyao1101@hotmail.com
License: MIT
Platform: UNKNOWN
Classifier: Topic :: Software Development :: Libraries :: Python Modules
Classifier: Programming Language :: Python :: 3
Classifier: Programming Language :: Python :: 3.8
Classifier: Programming Language :: Python :: 3.9
Classifier: Programming Language :: Python :: 3.10
Classifier: License :: OSI Approved :: MIT License
Classifier: Operating System :: OS Independent
Requires-Python: >=3.8
License-File: LICENSE
Requires-Dist: pygments
